mlx/xunit2rst/__init__.py
mlx/xunit2rst/__main__.py
mlx/xunit2rst/__version__.py
mlx/xunit2rst/xunit2rst.mako
mlx/xunit2rst/xunit2rst.py
mlx/xunit2rst/assets/xunit2rst.css
mlx_xunit2rst-2.2.0.dist-info/licenses/LICENSE
mlx_xunit2rst-2.2.0.dist-info/METADATA
mlx_xunit2rst-2.2.0.dist-info/WHEEL
mlx_xunit2rst-2.2.0.dist-info/entry_points.txt
mlx_xunit2rst-2.2.0.dist-info/top_level.txt
mlx_xunit2rst-2.2.0.dist-info/RECORD
