Metadata-Version: 2.4
Name: mlx.xunit2rst
Version: 2.2.0
Summary: Python script for converting xUnit/JUnit XML format to reStructuredText (.rst) with traceable items
Home-page: https://github.com/melexis/xunit2rst
Author: JasperCraeghs
Author-email: jce@melexis.com
License: Apache-2.0
Keywords: xUnit,JUnit,XML,reStructuredText,sphinx,rst,testing,traceability,documentation
Platform: any
Classifier: Development Status :: 5 - Production/Stable
Classifier: Environment :: Console
Classifier: Intended Audience :: Developers
Classifier: Operating System :: OS Independent
Classifier: Programming Language :: Python
Classifier: Programming Language :: Python :: 3
Classifier: Programming Language :: Python :: 3.8
Classifier: Programming Language :: Python :: 3.9
Classifier: Programming Language :: Python :: 3.10
Classifier: Programming Language :: Python :: 3.11
Classifier: Programming Language :: Python :: 3.12
Classifier: Topic :: Documentation
Classifier: Topic :: Documentation :: Sphinx
Classifier: Topic :: Utilities
Requires-Python: >=3.8
License-File: LICENSE
Requires-Dist: mako
Requires-Dist: ruamel.yaml>=0.17.21
Dynamic: author
Dynamic: author-email
Dynamic: classifier
Dynamic: description
Dynamic: description-content-type
Dynamic: home-page
Dynamic: keywords
Dynamic: license
Dynamic: license-file
Dynamic: platform
Dynamic: requires-dist
Dynamic: requires-python
Dynamic: summary
